[
  {
    "teamKey": "2025-2026::2A. TERRITORIAL SENIOR FEMENI::TEAM:78662",
    "teamIdIntern": 452578,
    "teamIdExtern": 78662,
    "teamName": "DROOP CENTRE C.B. L\u0027HOSPITALET",
    "seasonStartYear": 2025,
    "seasonLabel": "2025-2026",
    "homeTeamKey": "2025-2026::2A. TERRITORIAL SENIOR FEMENI::TEAM:78662",
    "awayTeamKey": "2025-2026::2A. TERRITORIAL SENIOR FEMENI::TEAM:79097",
    "matchWebId": 18527,
    "matchInternId": 224986,
    "matchExternId": 1068451,
    "matchDate": "2025-09-28T12:45:00+02:00",
    "phaseNumber": 1,
    "sourcePhaseId": 19989,
    "categoryName": "2a. Territorial S\u00E8nior Femen\u00ED",
    "phaseName": "Fase Regular",
    "levelName": "",
    "levelCode": "",
    "groupCode": "06",
    "phaseRound": 1,
    "roundNumber": 1,
    "homeTeam": "DROOP CENTRE C.B. L\u0027HOSPITALET",
    "homeScore": 53,
    "awayScore": 47,
    "awayTeam": "UE SANT ANDREU A",
    "isHome": true,
    "rivalTeamKey": "2025-2026::2A. TERRITORIAL SENIOR FEMENI::TEAM:79097",
    "rivalTeam": "UE SANT ANDREU A",
    "officialTeamScore": 53,
    "officialRivalScore": 47,
    "teamScore": 53,
    "rivalScore": 47,
    "result": "W",
    "topScorer": "HELENA BRIEGAS PORRAS",
    "topScorerTeam": "DROOP CENTRE C.B. L\u0027HOSPITALET",
    "topScorerPoints": 21,
    "teamTopScorer": "HELENA BRIEGAS PORRAS",
    "teamTopScorerPoints": 21,
    "insights": {
      "leadChanges": 0,
      "ties": 0,
      "maxLead": 10,
      "maxDeficit": 0,
      "bestRun": 5,
      "rivalBestRun": 5,
      "closingRun": 0,
      "rivalClosingRun": 4,
      "firstScorer": "ISABEL RUIZ VILASECA",
      "firstScorerTeam": "DROOP CENTRE C.B. L\u0027HOSPITALET",
      "lastScorer": "ELSA HURTADO ALVAREZ",
      "lastScorerTeam": "UE SANT ANDREU A",
      "teamFirstScorer": "ISABEL RUIZ VILASECA",
      "teamLastScorer": "CARLA GOMEZ MART\u00CDN",
      "bestPeriodLabel": "Parcial 1",
      "bestPeriodDiff": 7,
      "worstPeriodLabel": "Parcial 2",
      "worstPeriodDiff": -5,
      "periodScores": [
        {
          "periodNumber": 1,
          "label": "Parcial 1",
          "teamPoints": 18,
          "rivalPoints": 11,
          "diff": 7
        },
        {
          "periodNumber": 2,
          "label": "Parcial 2",
          "teamPoints": 6,
          "rivalPoints": 11,
          "diff": -5
        },
        {
          "periodNumber": 3,
          "label": "Parcial 3",
          "teamPoints": 19,
          "rivalPoints": 15,
          "diff": 4
        },
        {
          "periodNumber": 4,
          "label": "Parcial 4",
          "teamPoints": 10,
          "rivalPoints": 10,
          "diff": 0
        }
      ]
    },
    "matchReport": "",
    "matchReportGeneratedAtUtc": null,
    "matchReportModel": ""
  },
  {
    "teamKey": "2025-2026::2A. TERRITORIAL SENIOR FEMENI::TEAM:78662",
    "teamIdIntern": 457797,
    "teamIdExtern": 78662,
    "teamName": "DROOP CENTRE C.B. L\u0027HOSPITALET",
    "seasonStartYear": 2025,
    "seasonLabel": "2025-2026",
    "homeTeamKey": "2025-2026::2A. TERRITORIAL SENIOR FEMENI::TEAM:81439",
    "awayTeamKey": "2025-2026::2A. TERRITORIAL SENIOR FEMENI::TEAM:78662",
    "matchWebId": 18535,
    "matchInternId": 227595,
    "matchExternId": 1068459,
    "matchDate": "2025-10-05T21:00:00+02:00",
    "phaseNumber": 1,
    "sourcePhaseId": 19989,
    "categoryName": "2a. Territorial S\u00E8nior Femen\u00ED",
    "phaseName": "Fase Regular",
    "levelName": "",
    "levelCode": "",
    "groupCode": "06",
    "phaseRound": 2,
    "roundNumber": 2,
    "homeTeam": "JESU\u00CFTES GR\u00C0CIA KOSTKA",
    "homeScore": 61,
    "awayScore": 53,
    "awayTeam": "DROOP CENTRE C.B. L\u0027HOSPITALET",
    "isHome": false,
    "rivalTeamKey": "2025-2026::2A. TERRITORIAL SENIOR FEMENI::TEAM:81439",
    "rivalTeam": "JESU\u00CFTES GR\u00C0CIA KOSTKA",
    "officialTeamScore": 53,
    "officialRivalScore": 61,
    "teamScore": 53,
    "rivalScore": 61,
    "result": "L",
    "topScorer": "HELENA BRIEGAS PORRAS",
    "topScorerTeam": "DROOP CENTRE C.B. L\u0027HOSPITALET",
    "topScorerPoints": 16,
    "teamTopScorer": "HELENA BRIEGAS PORRAS",
    "teamTopScorerPoints": 16,
    "insights": {
      "leadChanges": 4,
      "ties": 5,
      "maxLead": 8,
      "maxDeficit": 11,
      "bestRun": 9,
      "rivalBestRun": 8,
      "closingRun": 3,
      "rivalClosingRun": 0,
      "firstScorer": "NOA GARCIA OREJA",
      "firstScorerTeam": "DROOP CENTRE C.B. L\u0027HOSPITALET",
      "lastScorer": "HELENA BRIEGAS PORRAS",
      "lastScorerTeam": "DROOP CENTRE C.B. L\u0027HOSPITALET",
      "teamFirstScorer": "NOA GARCIA OREJA",
      "teamLastScorer": "HELENA BRIEGAS PORRAS",
      "bestPeriodLabel": "Parcial 1",
      "bestPeriodDiff": -1,
      "worstPeriodLabel": "Parcial 2",
      "worstPeriodDiff": -3,
      "periodScores": [
        {
          "periodNumber": 1,
          "label": "Parcial 1",
          "teamPoints": 15,
          "rivalPoints": 16,
          "diff": -1
        },
        {
          "periodNumber": 2,
          "label": "Parcial 2",
          "teamPoints": 8,
          "rivalPoints": 11,
          "diff": -3
        },
        {
          "periodNumber": 3,
          "label": "Parcial 3",
          "teamPoints": 12,
          "rivalPoints": 15,
          "diff": -3
        },
        {
          "periodNumber": 4,
          "label": "Parcial 4",
          "teamPoints": 18,
          "rivalPoints": 19,
          "diff": -1
        }
      ]
    },
    "matchReport": "",
    "matchReportGeneratedAtUtc": null,
    "matchReportModel": ""
  },
  {
    "teamKey": "2025-2026::2A. TERRITORIAL SENIOR FEMENI::TEAM:78662",
    "teamIdIntern": 467203,
    "teamIdExtern": 78662,
    "teamName": "DROOP CENTRE C.B. L\u0027HOSPITALET",
    "seasonStartYear": 2025,
    "seasonLabel": "2025-2026",
    "homeTeamKey": "2025-2026::2A. TERRITORIAL SENIOR FEMENI::TEAM:79306",
    "awayTeamKey": "2025-2026::2A. TERRITORIAL SENIOR FEMENI::TEAM:78662",
    "matchWebId": 18550,
    "matchInternId": 232298,
    "matchExternId": 1068474,
    "matchDate": "2025-10-19T20:00:00+02:00",
    "phaseNumber": 1,
    "sourcePhaseId": 19989,
    "categoryName": "2a. Territorial S\u00E8nior Femen\u00ED",
    "phaseName": "Fase Regular",
    "levelName": "",
    "levelCode": "",
    "groupCode": "06",
    "phaseRound": 3,
    "roundNumber": 3,
    "homeTeam": "UE BARBERA",
    "homeScore": 52,
    "awayScore": 59,
    "awayTeam": "DROOP CENTRE C.B. L\u0027HOSPITALET",
    "isHome": false,
    "rivalTeamKey": "2025-2026::2A. TERRITORIAL SENIOR FEMENI::TEAM:79306",
    "rivalTeam": "UE BARBERA",
    "officialTeamScore": 59,
    "officialRivalScore": 52,
    "teamScore": 59,
    "rivalScore": 52,
    "result": "W",
    "topScorer": "HELENA BRIEGAS PORRAS",
    "topScorerTeam": "DROOP CENTRE C.B. L\u0027HOSPITALET",
    "topScorerPoints": 13,
    "teamTopScorer": "HELENA BRIEGAS PORRAS",
    "teamTopScorerPoints": 13,
    "insights": {
      "leadChanges": 3,
      "ties": 5,
      "maxLead": 10,
      "maxDeficit": 7,
      "bestRun": 7,
      "rivalBestRun": 6,
      "closingRun": 0,
      "rivalClosingRun": 1,
      "firstScorer": "GEMMA ROJALS SERRANO",
      "firstScorerTeam": "DROOP CENTRE C.B. L\u0027HOSPITALET",
      "lastScorer": "MARTA GARCIA MORILLAS",
      "lastScorerTeam": "UE BARBERA",
      "teamFirstScorer": "GEMMA ROJALS SERRANO",
      "teamLastScorer": "HELENA BRIEGAS PORRAS",
      "bestPeriodLabel": "Parcial 3",
      "bestPeriodDiff": 9,
      "worstPeriodLabel": "Parcial 2",
      "worstPeriodDiff": -11,
      "periodScores": [
        {
          "periodNumber": 1,
          "label": "Parcial 1",
          "teamPoints": 18,
          "rivalPoints": 14,
          "diff": 4
        },
        {
          "periodNumber": 2,
          "label": "Parcial 2",
          "teamPoints": 8,
          "rivalPoints": 19,
          "diff": -11
        },
        {
          "periodNumber": 3,
          "label": "Parcial 3",
          "teamPoints": 14,
          "rivalPoints": 5,
          "diff": 9
        },
        {
          "periodNumber": 4,
          "label": "Parcial 4",
          "teamPoints": 19,
          "rivalPoints": 14,
          "diff": 5
        }
      ]
    },
    "matchReport": "",
    "matchReportGeneratedAtUtc": null,
    "matchReportModel": ""
  },
  {
    "teamKey": "2025-2026::2A. TERRITORIAL SENIOR FEMENI::TEAM:78662",
    "teamIdIntern": 471556,
    "teamIdExtern": 78662,
    "teamName": "DROOP CENTRE C.B. L\u0027HOSPITALET",
    "seasonStartYear": 2025,
    "seasonLabel": "2025-2026",
    "homeTeamKey": "2025-2026::2A. TERRITORIAL SENIOR FEMENI::TEAM:78662",
    "awayTeamKey": "2025-2026::2A. TERRITORIAL SENIOR FEMENI::TEAM:79004",
    "matchWebId": 18555,
    "matchInternId": 234475,
    "matchExternId": 1092704,
    "matchDate": "2025-10-26T13:30:00+01:00",
    "phaseNumber": 1,
    "sourcePhaseId": 19989,
    "categoryName": "2a. Territorial S\u00E8nior Femen\u00ED",
    "phaseName": "Fase Regular",
    "levelName": "",
    "levelCode": "",
    "groupCode": "06",
    "phaseRound": 4,
    "roundNumber": 4,
    "homeTeam": "DROOP CENTRE C.B. L\u0027HOSPITALET",
    "homeScore": 57,
    "awayScore": 40,
    "awayTeam": "EL C\u00CDRCOL B",
    "isHome": true,
    "rivalTeamKey": "2025-2026::2A. TERRITORIAL SENIOR FEMENI::TEAM:79004",
    "rivalTeam": "EL C\u00CDRCOL B",
    "officialTeamScore": 57,
    "officialRivalScore": 40,
    "teamScore": 57,
    "rivalScore": 40,
    "result": "W",
    "topScorer": "CARLA GOMEZ MART\u00CDN",
    "topScorerTeam": "DROOP CENTRE C.B. L\u0027HOSPITALET",
    "topScorerPoints": 18,
    "teamTopScorer": "CARLA GOMEZ MART\u00CDN",
    "teamTopScorerPoints": 18,
    "insights": {
      "leadChanges": 0,
      "ties": 2,
      "maxLead": 24,
      "maxDeficit": 2,
      "bestRun": 12,
      "rivalBestRun": 7,
      "closingRun": 0,
      "rivalClosingRun": 7,
      "firstScorer": "MARTINA TOMAS LUQUE",
      "firstScorerTeam": "EL C\u00CDRCOL B",
      "lastScorer": "MAR GUBERN DELTORO",
      "lastScorerTeam": "EL C\u00CDRCOL B",
      "teamFirstScorer": "HELENA BRIEGAS PORRAS",
      "teamLastScorer": "ANDREA ESPADA PEREZ",
      "bestPeriodLabel": "Parcial 1",
      "bestPeriodDiff": 9,
      "worstPeriodLabel": "Parcial 4",
      "worstPeriodDiff": -2,
      "periodScores": [
        {
          "periodNumber": 1,
          "label": "Parcial 1",
          "teamPoints": 16,
          "rivalPoints": 7,
          "diff": 9
        },
        {
          "periodNumber": 2,
          "label": "Parcial 2",
          "teamPoints": 14,
          "rivalPoints": 12,
          "diff": 2
        },
        {
          "periodNumber": 3,
          "label": "Parcial 3",
          "teamPoints": 14,
          "rivalPoints": 6,
          "diff": 8
        },
        {
          "periodNumber": 4,
          "label": "Parcial 4",
          "teamPoints": 13,
          "rivalPoints": 15,
          "diff": -2
        }
      ]
    },
    "matchReport": "",
    "matchReportGeneratedAtUtc": null,
    "matchReportModel": ""
  },
  {
    "teamKey": "2025-2026::2A. TERRITORIAL SENIOR FEMENI::TEAM:78662",
    "teamIdIntern": 472876,
    "teamIdExtern": 78662,
    "teamName": "DROOP CENTRE C.B. L\u0027HOSPITALET",
    "seasonStartYear": 2025,
    "seasonLabel": "2025-2026",
    "homeTeamKey": "2025-2026::2A. TERRITORIAL SENIOR FEMENI::TEAM:78662",
    "awayTeamKey": "2025-2026::2A. TERRITORIAL SENIOR FEMENI::TEAM:82327",
    "matchWebId": 18541,
    "matchInternId": 235135,
    "matchExternId": 1092797,
    "matchDate": "2025-11-02T13:30:00+01:00",
    "phaseNumber": 1,
    "sourcePhaseId": 19989,
    "categoryName": "2a. Territorial S\u00E8nior Femen\u00ED",
    "phaseName": "Fase Regular",
    "levelName": "",
    "levelCode": "",
    "groupCode": "06",
    "phaseRound": 5,
    "roundNumber": 5,
    "homeTeam": "DROOP CENTRE C.B. L\u0027HOSPITALET",
    "homeScore": 68,
    "awayScore": 31,
    "awayTeam": "UE SANT CUGAT - OCCIDENT C",
    "isHome": true,
    "rivalTeamKey": "2025-2026::2A. TERRITORIAL SENIOR FEMENI::TEAM:82327",
    "rivalTeam": "UE SANT CUGAT - OCCIDENT C",
    "officialTeamScore": 68,
    "officialRivalScore": 31,
    "teamScore": 68,
    "rivalScore": 31,
    "result": "W",
    "topScorer": "CRISTINA GIRAL GOZALVEZ",
    "topScorerTeam": "DROOP CENTRE C.B. L\u0027HOSPITALET",
    "topScorerPoints": 12,
    "teamTopScorer": "CRISTINA GIRAL GOZALVEZ",
    "teamTopScorerPoints": 12,
    "insights": {
      "leadChanges": 2,
      "ties": 3,
      "maxLead": 40,
      "maxDeficit": 2,
      "bestRun": 16,
      "rivalBestRun": 5,
      "closingRun": 0,
      "rivalClosingRun": 3,
      "firstScorer": "SARA MERINO MARFIL",
      "firstScorerTeam": "UE SANT CUGAT - OCCIDENT C",
      "lastScorer": "JULIA LIMONERO GOMEZ",
      "lastScorerTeam": "UE SANT CUGAT - OCCIDENT C",
      "teamFirstScorer": "NOA GARCIA OREJA",
      "teamLastScorer": "AMALIA TAJES GUILLEN",
      "bestPeriodLabel": "Parcial 2",
      "bestPeriodDiff": 11,
      "worstPeriodLabel": "Parcial 1",
      "worstPeriodDiff": 8,
      "periodScores": [
        {
          "periodNumber": 1,
          "label": "Parcial 1",
          "teamPoints": 17,
          "rivalPoints": 9,
          "diff": 8
        },
        {
          "periodNumber": 2,
          "label": "Parcial 2",
          "teamPoints": 15,
          "rivalPoints": 4,
          "diff": 11
        },
        {
          "periodNumber": 3,
          "label": "Parcial 3",
          "teamPoints": 15,
          "rivalPoints": 7,
          "diff": 8
        },
        {
          "periodNumber": 4,
          "label": "Parcial 4",
          "teamPoints": 21,
          "rivalPoints": 11,
          "diff": 10
        }
      ]
    },
    "matchReport": "",
    "matchReportGeneratedAtUtc": null,
    "matchReportModel": ""
  },
  {
    "teamKey": "2025-2026::2A. TERRITORIAL SENIOR FEMENI::TEAM:78662",
    "teamIdIntern": 476777,
    "teamIdExtern": 78662,
    "teamName": "DROOP CENTRE C.B. L\u0027HOSPITALET",
    "seasonStartYear": 2025,
    "seasonLabel": "2025-2026",
    "homeTeamKey": "2025-2026::2A. TERRITORIAL SENIOR FEMENI::TEAM:83121",
    "awayTeamKey": "2025-2026::2A. TERRITORIAL SENIOR FEMENI::TEAM:78662",
    "matchWebId": 18565,
    "matchInternId": 237085,
    "matchExternId": 1068489,
    "matchDate": "2025-11-09T11:45:00+01:00",
    "phaseNumber": 1,
    "sourcePhaseId": 19989,
    "categoryName": "2a. Territorial S\u00E8nior Femen\u00ED",
    "phaseName": "Fase Regular",
    "levelName": "",
    "levelCode": "",
    "groupCode": "06",
    "phaseRound": 6,
    "roundNumber": 6,
    "homeTeam": "AEC COLLBLANC B",
    "homeScore": 58,
    "awayScore": 64,
    "awayTeam": "DROOP CENTRE C.B. L\u0027HOSPITALET",
    "isHome": false,
    "rivalTeamKey": "2025-2026::2A. TERRITORIAL SENIOR FEMENI::TEAM:83121",
    "rivalTeam": "AEC COLLBLANC B",
    "officialTeamScore": 64,
    "officialRivalScore": 58,
    "teamScore": 64,
    "rivalScore": 58,
    "result": "W",
    "topScorer": "CLARA SALOM ESTELA",
    "topScorerTeam": "AEC COLLBLANC B",
    "topScorerPoints": 15,
    "teamTopScorer": "LAIA MOLINA QUILES",
    "teamTopScorerPoints": 12,
    "insights": {
      "leadChanges": 0,
      "ties": 1,
      "maxLead": 14,
      "maxDeficit": 0,
      "bestRun": 9,
      "rivalBestRun": 12,
      "closingRun": 0,
      "rivalClosingRun": 4,
      "firstScorer": "LAIA TORRAS DOMINGUEZ",
      "firstScorerTeam": "DROOP CENTRE C.B. L\u0027HOSPITALET",
      "lastScorer": "CLARA SALOM ESTELA",
      "lastScorerTeam": "AEC COLLBLANC B",
      "teamFirstScorer": "LAIA TORRAS DOMINGUEZ",
      "teamLastScorer": "GEMMA ROJALS SERRANO",
      "bestPeriodLabel": "Parcial 2",
      "bestPeriodDiff": 10,
      "worstPeriodLabel": "Parcial 3",
      "worstPeriodDiff": -4,
      "periodScores": [
        {
          "periodNumber": 1,
          "label": "Parcial 1",
          "teamPoints": 15,
          "rivalPoints": 12,
          "diff": 3
        },
        {
          "periodNumber": 2,
          "label": "Parcial 2",
          "teamPoints": 21,
          "rivalPoints": 11,
          "diff": 10
        },
        {
          "periodNumber": 3,
          "label": "Parcial 3",
          "teamPoints": 13,
          "rivalPoints": 17,
          "diff": -4
        },
        {
          "periodNumber": 4,
          "label": "Parcial 4",
          "teamPoints": 15,
          "rivalPoints": 18,
          "diff": -3
        }
      ]
    },
    "matchReport": "",
    "matchReportGeneratedAtUtc": null,
    "matchReportModel": ""
  },
  {
    "teamKey": "2025-2026::2A. TERRITORIAL SENIOR FEMENI::TEAM:78662",
    "teamIdIntern": 481096,
    "teamIdExtern": 78662,
    "teamName": "DROOP CENTRE C.B. L\u0027HOSPITALET",
    "seasonStartYear": 2025,
    "seasonLabel": "2025-2026",
    "homeTeamKey": "2025-2026::2A. TERRITORIAL SENIOR FEMENI::TEAM:78662",
    "awayTeamKey": "2025-2026::2A. TERRITORIAL SENIOR FEMENI::TEAM:81851",
    "matchWebId": 18569,
    "matchInternId": 239245,
    "matchExternId": 1099634,
    "matchDate": "2025-11-15T21:00:00+01:00",
    "phaseNumber": 1,
    "sourcePhaseId": 19989,
    "categoryName": "2a. Territorial S\u00E8nior Femen\u00ED",
    "phaseName": "Fase Regular",
    "levelName": "",
    "levelCode": "",
    "groupCode": "06",
    "phaseRound": 7,
    "roundNumber": 7,
    "homeTeam": "DROOP CENTRE C.B. L\u0027HOSPITALET",
    "homeScore": 60,
    "awayScore": 55,
    "awayTeam": "B\u00C0SQUET NOU BARRIS",
    "isHome": true,
    "rivalTeamKey": "2025-2026::2A. TERRITORIAL SENIOR FEMENI::TEAM:81851",
    "rivalTeam": "B\u00C0SQUET NOU BARRIS",
    "officialTeamScore": 60,
    "officialRivalScore": 55,
    "teamScore": 60,
    "rivalScore": 55,
    "result": "W",
    "topScorer": "JULIA GIMENEZ SOGUES",
    "topScorerTeam": "B\u00C0SQUET NOU BARRIS",
    "topScorerPoints": 18,
    "teamTopScorer": "CARLA GOMEZ MART\u00CDN",
    "teamTopScorerPoints": 12,
    "insights": {
      "leadChanges": 1,
      "ties": 4,
      "maxLead": 17,
      "maxDeficit": 7,
      "bestRun": 11,
      "rivalBestRun": 8,
      "closingRun": 2,
      "rivalClosingRun": 0,
      "firstScorer": "ALBA GUERRERO GARCIA",
      "firstScorerTeam": "B\u00C0SQUET NOU BARRIS",
      "lastScorer": "HELENA BRIEGAS PORRAS",
      "lastScorerTeam": "DROOP CENTRE C.B. L\u0027HOSPITALET",
      "teamFirstScorer": "HELENA BRIEGAS PORRAS",
      "teamLastScorer": "HELENA BRIEGAS PORRAS",
      "bestPeriodLabel": "Parcial 3",
      "bestPeriodDiff": 4,
      "worstPeriodLabel": "Parcial 4",
      "worstPeriodDiff": -5,
      "periodScores": [
        {
          "periodNumber": 1,
          "label": "Parcial 1",
          "teamPoints": 17,
          "rivalPoints": 14,
          "diff": 3
        },
        {
          "periodNumber": 2,
          "label": "Parcial 2",
          "teamPoints": 18,
          "rivalPoints": 15,
          "diff": 3
        },
        {
          "periodNumber": 3,
          "label": "Parcial 3",
          "teamPoints": 15,
          "rivalPoints": 11,
          "diff": 4
        },
        {
          "periodNumber": 4,
          "label": "Parcial 4",
          "teamPoints": 10,
          "rivalPoints": 15,
          "diff": -5
        }
      ]
    },
    "matchReport": "",
    "matchReportGeneratedAtUtc": null,
    "matchReportModel": ""
  },
  {
    "teamKey": "2025-2026::2A. TERRITORIAL SENIOR FEMENI::TEAM:78662",
    "teamIdIntern": 486831,
    "teamIdExtern": 78662,
    "teamName": "DROOP CENTRE C.B. L\u0027HOSPITALET",
    "seasonStartYear": 2025,
    "seasonLabel": "2025-2026",
    "homeTeamKey": "2025-2026::2A. TERRITORIAL SENIOR FEMENI::TEAM:81725",
    "awayTeamKey": "2025-2026::2A. TERRITORIAL SENIOR FEMENI::TEAM:78662",
    "matchWebId": 18580,
    "matchInternId": 242113,
    "matchExternId": 1108424,
    "matchDate": "2025-11-23T13:45:00+01:00",
    "phaseNumber": 1,
    "sourcePhaseId": 19989,
    "categoryName": "2a. Territorial S\u00E8nior Femen\u00ED",
    "phaseName": "Fase Regular",
    "levelName": "",
    "levelCode": "",
    "groupCode": "06",
    "phaseRound": 8,
    "roundNumber": 8,
    "homeTeam": "CB ABRERA",
    "homeScore": 33,
    "awayScore": 60,
    "awayTeam": "DROOP CENTRE C.B. L\u0027HOSPITALET",
    "isHome": false,
    "rivalTeamKey": "2025-2026::2A. TERRITORIAL SENIOR FEMENI::TEAM:81725",
    "rivalTeam": "CB ABRERA",
    "officialTeamScore": 60,
    "officialRivalScore": 33,
    "teamScore": 60,
    "rivalScore": 33,
    "result": "W",
    "topScorer": "HELENA BRIEGAS PORRAS",
    "topScorerTeam": "DROOP CENTRE C.B. L\u0027HOSPITALET",
    "topScorerPoints": 9,
    "teamTopScorer": "HELENA BRIEGAS PORRAS",
    "teamTopScorerPoints": 9,
    "insights": {
      "leadChanges": 1,
      "ties": 1,
      "maxLead": 27,
      "maxDeficit": 2,
      "bestRun": 10,
      "rivalBestRun": 5,
      "closingRun": 6,
      "rivalClosingRun": 0,
      "firstScorer": "DULCE POLO PEREZ",
      "firstScorerTeam": "CB ABRERA",
      "lastScorer": "GEMMA ROJALS SERRANO",
      "lastScorerTeam": "DROOP CENTRE C.B. L\u0027HOSPITALET",
      "teamFirstScorer": "ISABEL RUIZ VILASECA",
      "teamLastScorer": "GEMMA ROJALS SERRANO",
      "bestPeriodLabel": "Parcial 1",
      "bestPeriodDiff": 12,
      "worstPeriodLabel": "Parcial 2",
      "worstPeriodDiff": 3,
      "periodScores": [
        {
          "periodNumber": 1,
          "label": "Parcial 1",
          "teamPoints": 19,
          "rivalPoints": 7,
          "diff": 12
        },
        {
          "periodNumber": 2,
          "label": "Parcial 2",
          "teamPoints": 14,
          "rivalPoints": 11,
          "diff": 3
        },
        {
          "periodNumber": 3,
          "label": "Parcial 3",
          "teamPoints": 14,
          "rivalPoints": 10,
          "diff": 4
        },
        {
          "periodNumber": 4,
          "label": "Parcial 4",
          "teamPoints": 13,
          "rivalPoints": 5,
          "diff": 8
        }
      ]
    },
    "matchReport": "",
    "matchReportGeneratedAtUtc": null,
    "matchReportModel": ""
  },
  {
    "teamKey": "2025-2026::2A. TERRITORIAL SENIOR FEMENI::TEAM:78662",
    "teamIdIntern": 489938,
    "teamIdExtern": 78662,
    "teamName": "DROOP CENTRE C.B. L\u0027HOSPITALET",
    "seasonStartYear": 2025,
    "seasonLabel": "2025-2026",
    "homeTeamKey": "2025-2026::2A. TERRITORIAL SENIOR FEMENI::TEAM:78662",
    "awayTeamKey": "2025-2026::2A. TERRITORIAL SENIOR FEMENI::TEAM:83244",
    "matchWebId": 18583,
    "matchInternId": 243667,
    "matchExternId": 1092750,
    "matchDate": "2025-11-29T16:45:00+01:00",
    "phaseNumber": 1,
    "sourcePhaseId": 19989,
    "categoryName": "2a. Territorial S\u00E8nior Femen\u00ED",
    "phaseName": "Fase Regular",
    "levelName": "",
    "levelCode": "",
    "groupCode": "06",
    "phaseRound": 9,
    "roundNumber": 9,
    "homeTeam": "DROOP CENTRE C.B. L\u0027HOSPITALET",
    "homeScore": 38,
    "awayScore": 51,
    "awayTeam": "CE LA MARINA",
    "isHome": true,
    "rivalTeamKey": "2025-2026::2A. TERRITORIAL SENIOR FEMENI::TEAM:83244",
    "rivalTeam": "CE LA MARINA",
    "officialTeamScore": 38,
    "officialRivalScore": 51,
    "teamScore": 38,
    "rivalScore": 51,
    "result": "L",
    "topScorer": "JUDIT PARDO SANROMA",
    "topScorerTeam": "CE LA MARINA",
    "topScorerPoints": 16,
    "teamTopScorer": "CARLA GOMEZ MART\u00CDN",
    "teamTopScorerPoints": 12,
    "insights": {
      "leadChanges": 2,
      "ties": 7,
      "maxLead": 5,
      "maxDeficit": 18,
      "bestRun": 6,
      "rivalBestRun": 7,
      "closingRun": 4,
      "rivalClosingRun": 0,
      "firstScorer": "JUDIT PARDO SANROMA",
      "firstScorerTeam": "CE LA MARINA",
      "lastScorer": "CARLA GOMEZ MART\u00CDN",
      "lastScorerTeam": "DROOP CENTRE C.B. L\u0027HOSPITALET",
      "teamFirstScorer": "LAIA MOLINA QUILES",
      "teamLastScorer": "CARLA GOMEZ MART\u00CDN",
      "bestPeriodLabel": "Parcial 1",
      "bestPeriodDiff": 3,
      "worstPeriodLabel": "Parcial 3",
      "worstPeriodDiff": -8,
      "periodScores": [
        {
          "periodNumber": 1,
          "label": "Parcial 1",
          "teamPoints": 13,
          "rivalPoints": 10,
          "diff": 3
        },
        {
          "periodNumber": 2,
          "label": "Parcial 2",
          "teamPoints": 7,
          "rivalPoints": 13,
          "diff": -6
        },
        {
          "periodNumber": 3,
          "label": "Parcial 3",
          "teamPoints": 6,
          "rivalPoints": 14,
          "diff": -8
        },
        {
          "periodNumber": 4,
          "label": "Parcial 4",
          "teamPoints": 12,
          "rivalPoints": 14,
          "diff": -2
        }
      ]
    },
    "matchReport": "",
    "matchReportGeneratedAtUtc": null,
    "matchReportModel": ""
  },
  {
    "teamKey": "2025-2026::2A. TERRITORIAL SENIOR FEMENI::TEAM:78662",
    "teamIdIntern": 497255,
    "teamIdExtern": 78662,
    "teamName": "DROOP CENTRE C.B. L\u0027HOSPITALET",
    "seasonStartYear": 2025,
    "seasonLabel": "2025-2026",
    "homeTeamKey": "2025-2026::2A. TERRITORIAL SENIOR FEMENI::TEAM:78982",
    "awayTeamKey": "2025-2026::2A. TERRITORIAL SENIOR FEMENI::TEAM:78662",
    "matchWebId": 18595,
    "matchInternId": 247325,
    "matchExternId": 1068519,
    "matchDate": "2025-12-14T19:00:00+01:00",
    "phaseNumber": 1,
    "sourcePhaseId": 19989,
    "categoryName": "2a. Territorial S\u00E8nior Femen\u00ED",
    "phaseName": "Fase Regular",
    "levelName": "",
    "levelCode": "",
    "groupCode": "06",
    "phaseRound": 10,
    "roundNumber": 10,
    "homeTeam": "VIROLAI NEGRE",
    "homeScore": 44,
    "awayScore": 48,
    "awayTeam": "DROOP CENTRE C.B. L\u0027HOSPITALET",
    "isHome": false,
    "rivalTeamKey": "2025-2026::2A. TERRITORIAL SENIOR FEMENI::TEAM:78982",
    "rivalTeam": "VIROLAI NEGRE",
    "officialTeamScore": 48,
    "officialRivalScore": 44,
    "teamScore": 48,
    "rivalScore": 44,
    "result": "W",
    "topScorer": "NOA GARCIA OREJA",
    "topScorerTeam": "DROOP CENTRE C.B. L\u0027HOSPITALET",
    "topScorerPoints": 14,
    "teamTopScorer": "NOA GARCIA OREJA",
    "teamTopScorerPoints": 14,
    "insights": {
      "leadChanges": 8,
      "ties": 2,
      "maxLead": 12,
      "maxDeficit": 2,
      "bestRun": 8,
      "rivalBestRun": 10,
      "closingRun": 5,
      "rivalClosingRun": 0,
      "firstScorer": "NOA GARCIA OREJA",
      "firstScorerTeam": "DROOP CENTRE C.B. L\u0027HOSPITALET",
      "lastScorer": "NOA GARCIA OREJA",
      "lastScorerTeam": "DROOP CENTRE C.B. L\u0027HOSPITALET",
      "teamFirstScorer": "NOA GARCIA OREJA",
      "teamLastScorer": "NOA GARCIA OREJA",
      "bestPeriodLabel": "Parcial 1",
      "bestPeriodDiff": 6,
      "worstPeriodLabel": "Parcial 3",
      "worstPeriodDiff": -6,
      "periodScores": [
        {
          "periodNumber": 1,
          "label": "Parcial 1",
          "teamPoints": 15,
          "rivalPoints": 9,
          "diff": 6
        },
        {
          "periodNumber": 2,
          "label": "Parcial 2",
          "teamPoints": 10,
          "rivalPoints": 8,
          "diff": 2
        },
        {
          "periodNumber": 3,
          "label": "Parcial 3",
          "teamPoints": 13,
          "rivalPoints": 19,
          "diff": -6
        },
        {
          "periodNumber": 4,
          "label": "Parcial 4",
          "teamPoints": 10,
          "rivalPoints": 8,
          "diff": 2
        }
      ]
    },
    "matchReport": "",
    "matchReportGeneratedAtUtc": null,
    "matchReportModel": ""
  },
  {
    "teamKey": "2025-2026::2A. TERRITORIAL SENIOR FEMENI::TEAM:78662",
    "teamIdIntern": 499900,
    "teamIdExtern": 78662,
    "teamName": "DROOP CENTRE C.B. L\u0027HOSPITALET",
    "seasonStartYear": 2025,
    "seasonLabel": "2025-2026",
    "homeTeamKey": "2025-2026::2A. TERRITORIAL SENIOR FEMENI::TEAM:78662",
    "awayTeamKey": "2025-2026::2A. TERRITORIAL SENIOR FEMENI::TEAM:80835",
    "matchWebId": 18597,
    "matchInternId": 248648,
    "matchExternId": 1107683,
    "matchDate": "2025-12-20T16:45:00+01:00",
    "phaseNumber": 1,
    "sourcePhaseId": 19989,
    "categoryName": "2a. Territorial S\u00E8nior Femen\u00ED",
    "phaseName": "Fase Regular",
    "levelName": "",
    "levelCode": "",
    "groupCode": "06",
    "phaseRound": 11,
    "roundNumber": 11,
    "homeTeam": "DROOP CENTRE C.B. L\u0027HOSPITALET",
    "homeScore": 65,
    "awayScore": 40,
    "awayTeam": "C.B.VILADECAVALLS",
    "isHome": true,
    "rivalTeamKey": "2025-2026::2A. TERRITORIAL SENIOR FEMENI::TEAM:80835",
    "rivalTeam": "C.B.VILADECAVALLS",
    "officialTeamScore": 65,
    "officialRivalScore": 40,
    "teamScore": 65,
    "rivalScore": 40,
    "result": "W",
    "topScorer": "LAIA MOLINA QUILES",
    "topScorerTeam": "DROOP CENTRE C.B. L\u0027HOSPITALET",
    "topScorerPoints": 12,
    "teamTopScorer": "LAIA MOLINA QUILES",
    "teamTopScorerPoints": 12,
    "insights": {
      "leadChanges": 0,
      "ties": 0,
      "maxLead": 25,
      "maxDeficit": 0,
      "bestRun": 16,
      "rivalBestRun": 10,
      "closingRun": 16,
      "rivalClosingRun": 0,
      "firstScorer": "NOA GARCIA OREJA",
      "firstScorerTeam": "DROOP CENTRE C.B. L\u0027HOSPITALET",
      "lastScorer": "ANDREA ESPADA PEREZ",
      "lastScorerTeam": "DROOP CENTRE C.B. L\u0027HOSPITALET",
      "teamFirstScorer": "NOA GARCIA OREJA",
      "teamLastScorer": "ANDREA ESPADA PEREZ",
      "bestPeriodLabel": "Parcial 4",
      "bestPeriodDiff": 19,
      "worstPeriodLabel": "Parcial 2",
      "worstPeriodDiff": -4,
      "periodScores": [
        {
          "periodNumber": 1,
          "label": "Parcial 1",
          "teamPoints": 22,
          "rivalPoints": 10,
          "diff": 12
        },
        {
          "periodNumber": 2,
          "label": "Parcial 2",
          "teamPoints": 11,
          "rivalPoints": 15,
          "diff": -4
        },
        {
          "periodNumber": 3,
          "label": "Parcial 3",
          "teamPoints": 9,
          "rivalPoints": 11,
          "diff": -2
        },
        {
          "periodNumber": 4,
          "label": "Parcial 4",
          "teamPoints": 23,
          "rivalPoints": 4,
          "diff": 19
        }
      ]
    },
    "matchReport": "",
    "matchReportGeneratedAtUtc": null,
    "matchReportModel": ""
  },
  {
    "teamKey": "2025-2026::2A. TERRITORIAL SENIOR FEMENI::TEAM:78662",
    "teamIdIntern": 503497,
    "teamIdExtern": 78662,
    "teamName": "DROOP CENTRE C.B. L\u0027HOSPITALET",
    "seasonStartYear": 2025,
    "seasonLabel": "2025-2026",
    "homeTeamKey": "2025-2026::2A. TERRITORIAL SENIOR FEMENI::TEAM:79614",
    "awayTeamKey": "2025-2026::2A. TERRITORIAL SENIOR FEMENI::TEAM:78662",
    "matchWebId": 18609,
    "matchInternId": 250446,
    "matchExternId": 1109739,
    "matchDate": "2026-01-10T16:30:00+01:00",
    "phaseNumber": 2,
    "sourcePhaseId": 19989,
    "categoryName": "2a. Territorial S\u00E8nior Femen\u00ED",
    "phaseName": "Fase Regular",
    "levelName": "",
    "levelCode": "",
    "groupCode": "06",
    "phaseRound": 1,
    "roundNumber": 12,
    "homeTeam": "B\u00C0SQUET CEISSA",
    "homeScore": 52,
    "awayScore": 64,
    "awayTeam": "DROOP CENTRE C.B. L\u0027HOSPITALET",
    "isHome": false,
    "rivalTeamKey": "2025-2026::2A. TERRITORIAL SENIOR FEMENI::TEAM:79614",
    "rivalTeam": "B\u00C0SQUET CEISSA",
    "officialTeamScore": 64,
    "officialRivalScore": 52,
    "teamScore": 64,
    "rivalScore": 52,
    "result": "W",
    "topScorer": "NOA GARCIA OREJA",
    "topScorerTeam": "DROOP CENTRE C.B. L\u0027HOSPITALET",
    "topScorerPoints": 14,
    "teamTopScorer": "NOA GARCIA OREJA",
    "teamTopScorerPoints": 14,
    "insights": {
      "leadChanges": 1,
      "ties": 3,
      "maxLead": 23,
      "maxDeficit": 3,
      "bestRun": 12,
      "rivalBestRun": 8,
      "closingRun": 1,
      "rivalClosingRun": 0,
      "firstScorer": "AMALIA TAJES GUILLEN",
      "firstScorerTeam": "DROOP CENTRE C.B. L\u0027HOSPITALET",
      "lastScorer": "HELENA BRIEGAS PORRAS",
      "lastScorerTeam": "DROOP CENTRE C.B. L\u0027HOSPITALET",
      "teamFirstScorer": "AMALIA TAJES GUILLEN",
      "teamLastScorer": "HELENA BRIEGAS PORRAS",
      "bestPeriodLabel": "Parcial 2",
      "bestPeriodDiff": 8,
      "worstPeriodLabel": "Parcial 4",
      "worstPeriodDiff": -4,
      "periodScores": [
        {
          "periodNumber": 1,
          "label": "Parcial 1",
          "teamPoints": 15,
          "rivalPoints": 15,
          "diff": 0
        },
        {
          "periodNumber": 2,
          "label": "Parcial 2",
          "teamPoints": 20,
          "rivalPoints": 12,
          "diff": 8
        },
        {
          "periodNumber": 3,
          "label": "Parcial 3",
          "teamPoints": 20,
          "rivalPoints": 12,
          "diff": 8
        },
        {
          "periodNumber": 4,
          "label": "Parcial 4",
          "teamPoints": 9,
          "rivalPoints": 13,
          "diff": -4
        }
      ]
    },
    "matchReport": "",
    "matchReportGeneratedAtUtc": null,
    "matchReportModel": ""
  },
  {
    "teamKey": "2025-2026::2A. TERRITORIAL SENIOR FEMENI::TEAM:78662",
    "teamIdIntern": 509760,
    "teamIdExtern": 78662,
    "teamName": "DROOP CENTRE C.B. L\u0027HOSPITALET",
    "seasonStartYear": 2025,
    "seasonLabel": "2025-2026",
    "homeTeamKey": "2025-2026::2A. TERRITORIAL SENIOR FEMENI::TEAM:78662",
    "awayTeamKey": "2025-2026::2A. TERRITORIAL SENIOR FEMENI::TEAM:79713",
    "matchWebId": 18611,
    "matchInternId": 253578,
    "matchExternId": 1123802,
    "matchDate": "2026-01-18T13:30:00+01:00",
    "phaseNumber": 2,
    "sourcePhaseId": 19989,
    "categoryName": "2a. Territorial S\u00E8nior Femen\u00ED",
    "phaseName": "Fase Regular",
    "levelName": "",
    "levelCode": "",
    "groupCode": "06",
    "phaseRound": 2,
    "roundNumber": 13,
    "homeTeam": "DROOP CENTRE C.B. L\u0027HOSPITALET",
    "homeScore": 65,
    "awayScore": 33,
    "awayTeam": "BC TECLA SALA  B",
    "isHome": true,
    "rivalTeamKey": "2025-2026::2A. TERRITORIAL SENIOR FEMENI::TEAM:79713",
    "rivalTeam": "BC TECLA SALA  B",
    "officialTeamScore": 65,
    "officialRivalScore": 33,
    "teamScore": 65,
    "rivalScore": 33,
    "result": "W",
    "topScorer": "NOA GARCIA OREJA",
    "topScorerTeam": "DROOP CENTRE C.B. L\u0027HOSPITALET",
    "topScorerPoints": 14,
    "teamTopScorer": "NOA GARCIA OREJA",
    "teamTopScorerPoints": 14,
    "insights": {
      "leadChanges": 0,
      "ties": 0,
      "maxLead": 32,
      "maxDeficit": 0,
      "bestRun": 14,
      "rivalBestRun": 6,
      "closingRun": 5,
      "rivalClosingRun": 0,
      "firstScorer": "AMALIA TAJES GUILLEN",
      "firstScorerTeam": "DROOP CENTRE C.B. L\u0027HOSPITALET",
      "lastScorer": "GEMMA ROJALS SERRANO",
      "lastScorerTeam": "DROOP CENTRE C.B. L\u0027HOSPITALET",
      "teamFirstScorer": "AMALIA TAJES GUILLEN",
      "teamLastScorer": "GEMMA ROJALS SERRANO",
      "bestPeriodLabel": "Parcial 2",
      "bestPeriodDiff": 12,
      "worstPeriodLabel": "Parcial 3",
      "worstPeriodDiff": 4,
      "periodScores": [
        {
          "periodNumber": 1,
          "label": "Parcial 1",
          "teamPoints": 16,
          "rivalPoints": 8,
          "diff": 8
        },
        {
          "periodNumber": 2,
          "label": "Parcial 2",
          "teamPoints": 19,
          "rivalPoints": 7,
          "diff": 12
        },
        {
          "periodNumber": 3,
          "label": "Parcial 3",
          "teamPoints": 13,
          "rivalPoints": 9,
          "diff": 4
        },
        {
          "periodNumber": 4,
          "label": "Parcial 4",
          "teamPoints": 17,
          "rivalPoints": 9,
          "diff": 8
        }
      ]
    },
    "matchReport": "",
    "matchReportGeneratedAtUtc": null,
    "matchReportModel": ""
  },
  {
    "teamKey": "2025-2026::2A. TERRITORIAL SENIOR FEMENI::TEAM:78662",
    "teamIdIntern": 515427,
    "teamIdExtern": 78662,
    "teamName": "DROOP CENTRE C.B. L\u0027HOSPITALET",
    "seasonStartYear": 2025,
    "seasonLabel": "2025-2026",
    "homeTeamKey": "2025-2026::2A. TERRITORIAL SENIOR FEMENI::TEAM:79097",
    "awayTeamKey": "2025-2026::2A. TERRITORIAL SENIOR FEMENI::TEAM:78662",
    "matchWebId": 18618,
    "matchInternId": 256411,
    "matchExternId": 1068542,
    "matchDate": "2026-01-25T20:20:00+01:00",
    "phaseNumber": 2,
    "sourcePhaseId": 19989,
    "categoryName": "2a. Territorial S\u00E8nior Femen\u00ED",
    "phaseName": "Fase Regular",
    "levelName": "",
    "levelCode": "",
    "groupCode": "06",
    "phaseRound": 3,
    "roundNumber": 14,
    "homeTeam": "UE SANT ANDREU A",
    "homeScore": 47,
    "awayScore": 65,
    "awayTeam": "DROOP CENTRE C.B. L\u0027HOSPITALET",
    "isHome": false,
    "rivalTeamKey": "2025-2026::2A. TERRITORIAL SENIOR FEMENI::TEAM:79097",
    "rivalTeam": "UE SANT ANDREU A",
    "officialTeamScore": 65,
    "officialRivalScore": 47,
    "teamScore": 65,
    "rivalScore": 47,
    "result": "W",
    "topScorer": "ANDREA TORRES LLEDO",
    "topScorerTeam": "UE SANT ANDREU A",
    "topScorerPoints": 12,
    "teamTopScorer": "LAIA MOLINA QUILES",
    "teamTopScorerPoints": 12,
    "insights": {
      "leadChanges": 2,
      "ties": 4,
      "maxLead": 21,
      "maxDeficit": 6,
      "bestRun": 9,
      "rivalBestRun": 8,
      "closingRun": 2,
      "rivalClosingRun": 0,
      "firstScorer": "ANDREA TORRES LLEDO",
      "firstScorerTeam": "UE SANT ANDREU A",
      "lastScorer": "LAIA MOLINA QUILES",
      "lastScorerTeam": "DROOP CENTRE C.B. L\u0027HOSPITALET",
      "teamFirstScorer": "GEMMA ROJALS SERRANO",
      "teamLastScorer": "LAIA MOLINA QUILES",
      "bestPeriodLabel": "Parcial 3",
      "bestPeriodDiff": 12,
      "worstPeriodLabel": "Parcial 4",
      "worstPeriodDiff": -3,
      "periodScores": [
        {
          "periodNumber": 1,
          "label": "Parcial 1",
          "teamPoints": 13,
          "rivalPoints": 12,
          "diff": 1
        },
        {
          "periodNumber": 2,
          "label": "Parcial 2",
          "teamPoints": 18,
          "rivalPoints": 10,
          "diff": 8
        },
        {
          "periodNumber": 3,
          "label": "Parcial 3",
          "teamPoints": 26,
          "rivalPoints": 14,
          "diff": 12
        },
        {
          "periodNumber": 4,
          "label": "Parcial 4",
          "teamPoints": 8,
          "rivalPoints": 11,
          "diff": -3
        }
      ]
    },
    "matchReport": "",
    "matchReportGeneratedAtUtc": null,
    "matchReportModel": ""
  },
  {
    "teamKey": "2025-2026::2A. TERRITORIAL SENIOR FEMENI::TEAM:78662",
    "teamIdIntern": 519458,
    "teamIdExtern": 78662,
    "teamName": "DROOP CENTRE C.B. L\u0027HOSPITALET",
    "seasonStartYear": 2025,
    "seasonLabel": "2025-2026",
    "homeTeamKey": "2025-2026::2A. TERRITORIAL SENIOR FEMENI::TEAM:78662",
    "awayTeamKey": "2025-2026::2A. TERRITORIAL SENIOR FEMENI::TEAM:81439",
    "matchWebId": 18626,
    "matchInternId": 258428,
    "matchExternId": 1144390,
    "matchDate": "2026-02-01T13:30:00+01:00",
    "phaseNumber": 2,
    "sourcePhaseId": 19989,
    "categoryName": "2a. Territorial S\u00E8nior Femen\u00ED",
    "phaseName": "Fase Regular",
    "levelName": "",
    "levelCode": "",
    "groupCode": "06",
    "phaseRound": 4,
    "roundNumber": 15,
    "homeTeam": "DROOP CENTRE C.B. L\u0027HOSPITALET",
    "homeScore": 56,
    "awayScore": 44,
    "awayTeam": "JESU\u00CFTES GR\u00C0CIA KOSTKA",
    "isHome": true,
    "rivalTeamKey": "2025-2026::2A. TERRITORIAL SENIOR FEMENI::TEAM:81439",
    "rivalTeam": "JESU\u00CFTES GR\u00C0CIA KOSTKA",
    "officialTeamScore": 56,
    "officialRivalScore": 44,
    "teamScore": 56,
    "rivalScore": 44,
    "result": "W",
    "topScorer": "MIA VIDAL PELLICER",
    "topScorerTeam": "JESU\u00CFTES GR\u00C0CIA KOSTKA",
    "topScorerPoints": 14,
    "teamTopScorer": "GEMMA ROJALS SERRANO",
    "teamTopScorerPoints": 10,
    "insights": {
      "leadChanges": 9,
      "ties": 4,
      "maxLead": 15,
      "maxDeficit": 2,
      "bestRun": 9,
      "rivalBestRun": 5,
      "closingRun": 2,
      "rivalClosingRun": 0,
      "firstScorer": "ABRIL BAG\u00DCESTE GASET",
      "firstScorerTeam": "JESU\u00CFTES GR\u00C0CIA KOSTKA",
      "lastScorer": "CRISTINA GIRAL GOZALVEZ",
      "lastScorerTeam": "DROOP CENTRE C.B. L\u0027HOSPITALET",
      "teamFirstScorer": "NOA GARCIA OREJA",
      "teamLastScorer": "CRISTINA GIRAL GOZALVEZ",
      "bestPeriodLabel": "Parcial 3",
      "bestPeriodDiff": 8,
      "worstPeriodLabel": "Parcial 4",
      "worstPeriodDiff": 0,
      "periodScores": [
        {
          "periodNumber": 1,
          "label": "Parcial 1",
          "teamPoints": 16,
          "rivalPoints": 15,
          "diff": 1
        },
        {
          "periodNumber": 2,
          "label": "Parcial 2",
          "teamPoints": 12,
          "rivalPoints": 9,
          "diff": 3
        },
        {
          "periodNumber": 3,
          "label": "Parcial 3",
          "teamPoints": 15,
          "rivalPoints": 7,
          "diff": 8
        },
        {
          "periodNumber": 4,
          "label": "Parcial 4",
          "teamPoints": 13,
          "rivalPoints": 13,
          "diff": 0
        }
      ]
    },
    "matchReport": "",
    "matchReportGeneratedAtUtc": null,
    "matchReportModel": ""
  },
  {
    "teamKey": "2025-2026::2A. TERRITORIAL SENIOR FEMENI::TEAM:78662",
    "teamIdIntern": 523691,
    "teamIdExtern": 78662,
    "teamName": "DROOP CENTRE C.B. L\u0027HOSPITALET",
    "seasonStartYear": 2025,
    "seasonLabel": "2025-2026",
    "homeTeamKey": "2025-2026::2A. TERRITORIAL SENIOR FEMENI::TEAM:82327",
    "awayTeamKey": "2025-2026::2A. TERRITORIAL SENIOR FEMENI::TEAM:78662",
    "matchWebId": 18632,
    "matchInternId": 260544,
    "matchExternId": 1148292,
    "matchDate": "2026-02-07T20:30:00+01:00",
    "phaseNumber": 2,
    "sourcePhaseId": 19989,
    "categoryName": "2a. Territorial S\u00E8nior Femen\u00ED",
    "phaseName": "Fase Regular",
    "levelName": "",
    "levelCode": "",
    "groupCode": "06",
    "phaseRound": 5,
    "roundNumber": 16,
    "homeTeam": "UE SANT CUGAT - OCCIDENT C",
    "homeScore": 43,
    "awayScore": 60,
    "awayTeam": "DROOP CENTRE C.B. L\u0027HOSPITALET",
    "isHome": false,
    "rivalTeamKey": "2025-2026::2A. TERRITORIAL SENIOR FEMENI::TEAM:82327",
    "rivalTeam": "UE SANT CUGAT - OCCIDENT C",
    "officialTeamScore": 60,
    "officialRivalScore": 43,
    "teamScore": 60,
    "rivalScore": 43,
    "result": "W",
    "topScorer": "GEMMA ROJALS SERRANO",
    "topScorerTeam": "DROOP CENTRE C.B. L\u0027HOSPITALET",
    "topScorerPoints": 20,
    "teamTopScorer": "GEMMA ROJALS SERRANO",
    "teamTopScorerPoints": 20,
    "insights": {
      "leadChanges": 0,
      "ties": 4,
      "maxLead": 18,
      "maxDeficit": 0,
      "bestRun": 8,
      "rivalBestRun": 4,
      "closingRun": 3,
      "rivalClosingRun": 0,
      "firstScorer": "GEMMA ROJALS SERRANO",
      "firstScorerTeam": "DROOP CENTRE C.B. L\u0027HOSPITALET",
      "lastScorer": "J\u00DALIA CABALLERO ALFONSO",
      "lastScorerTeam": "DROOP CENTRE C.B. L\u0027HOSPITALET",
      "teamFirstScorer": "GEMMA ROJALS SERRANO",
      "teamLastScorer": "J\u00DALIA CABALLERO ALFONSO",
      "bestPeriodLabel": "Parcial 4",
      "bestPeriodDiff": 8,
      "worstPeriodLabel": "Parcial 3",
      "worstPeriodDiff": 2,
      "periodScores": [
        {
          "periodNumber": 1,
          "label": "Parcial 1",
          "teamPoints": 19,
          "rivalPoints": 16,
          "diff": 3
        },
        {
          "periodNumber": 2,
          "label": "Parcial 2",
          "teamPoints": 13,
          "rivalPoints": 9,
          "diff": 4
        },
        {
          "periodNumber": 3,
          "label": "Parcial 3",
          "teamPoints": 11,
          "rivalPoints": 9,
          "diff": 2
        },
        {
          "periodNumber": 4,
          "label": "Parcial 4",
          "teamPoints": 17,
          "rivalPoints": 9,
          "diff": 8
        }
      ]
    },
    "matchReport": "",
    "matchReportGeneratedAtUtc": null,
    "matchReportModel": ""
  },
  {
    "teamKey": "2025-2026::2A. TERRITORIAL SENIOR FEMENI::TEAM:78662",
    "teamIdIntern": 534893,
    "teamIdExtern": 78662,
    "teamName": "DROOP CENTRE C.B. L\u0027HOSPITALET",
    "seasonStartYear": 2025,
    "seasonLabel": "2025-2026",
    "homeTeamKey": "2025-2026::2A. TERRITORIAL SENIOR FEMENI::TEAM:79004",
    "awayTeamKey": "2025-2026::2A. TERRITORIAL SENIOR FEMENI::TEAM:78662",
    "matchWebId": 18646,
    "matchInternId": 266145,
    "matchExternId": 1068570,
    "matchDate": "2026-03-01T11:45:00+01:00",
    "phaseNumber": 2,
    "sourcePhaseId": 19989,
    "categoryName": "2a. Territorial S\u00E8nior Femen\u00ED",
    "phaseName": "Fase Regular",
    "levelName": "",
    "levelCode": "",
    "groupCode": "06",
    "phaseRound": 6,
    "roundNumber": 17,
    "homeTeam": "EL C\u00CDRCOL B",
    "homeScore": 42,
    "awayScore": 60,
    "awayTeam": "DROOP CENTRE C.B. L\u0027HOSPITALET",
    "isHome": false,
    "rivalTeamKey": "2025-2026::2A. TERRITORIAL SENIOR FEMENI::TEAM:79004",
    "rivalTeam": "EL C\u00CDRCOL B",
    "officialTeamScore": 60,
    "officialRivalScore": 42,
    "teamScore": 60,
    "rivalScore": 42,
    "result": "W",
    "topScorer": "LAIA MOLINA QUILES",
    "topScorerTeam": "DROOP CENTRE C.B. L\u0027HOSPITALET",
    "topScorerPoints": 14,
    "teamTopScorer": "LAIA MOLINA QUILES",
    "teamTopScorerPoints": 14,
    "insights": {
      "leadChanges": 1,
      "ties": 3,
      "maxLead": 21,
      "maxDeficit": 5,
      "bestRun": 9,
      "rivalBestRun": 8,
      "closingRun": 4,
      "rivalClosingRun": 0,
      "firstScorer": "LAIA MOLINA QUILES",
      "firstScorerTeam": "DROOP CENTRE C.B. L\u0027HOSPITALET",
      "lastScorer": "GEMMA ROJALS SERRANO",
      "lastScorerTeam": "DROOP CENTRE C.B. L\u0027HOSPITALET",
      "teamFirstScorer": "LAIA MOLINA QUILES",
      "teamLastScorer": "GEMMA ROJALS SERRANO",
      "bestPeriodLabel": "Parcial 2",
      "bestPeriodDiff": 12,
      "worstPeriodLabel": "Parcial 1",
      "worstPeriodDiff": -5,
      "periodScores": [
        {
          "periodNumber": 1,
          "label": "Parcial 1",
          "teamPoints": 5,
          "rivalPoints": 10,
          "diff": -5
        },
        {
          "periodNumber": 2,
          "label": "Parcial 2",
          "teamPoints": 18,
          "rivalPoints": 6,
          "diff": 12
        },
        {
          "periodNumber": 3,
          "label": "Parcial 3",
          "teamPoints": 20,
          "rivalPoints": 9,
          "diff": 11
        },
        {
          "periodNumber": 4,
          "label": "Parcial 4",
          "teamPoints": 17,
          "rivalPoints": 17,
          "diff": 0
        }
      ]
    },
    "matchReport": "",
    "matchReportGeneratedAtUtc": null,
    "matchReportModel": ""
  },
  {
    "teamKey": "2025-2026::2A. TERRITORIAL SENIOR FEMENI::TEAM:78662",
    "teamIdIntern": 539186,
    "teamIdExtern": 78662,
    "teamName": "DROOP CENTRE C.B. L\u0027HOSPITALET",
    "seasonStartYear": 2025,
    "seasonLabel": "2025-2026",
    "homeTeamKey": "2025-2026::2A. TERRITORIAL SENIOR FEMENI::TEAM:78662",
    "awayTeamKey": "2025-2026::2A. TERRITORIAL SENIOR FEMENI::TEAM:83121",
    "matchWebId": 18656,
    "matchInternId": 268292,
    "matchExternId": 1144442,
    "matchDate": "2026-03-07T21:00:00+01:00",
    "phaseNumber": 2,
    "sourcePhaseId": 19989,
    "categoryName": "2a. Territorial S\u00E8nior Femen\u00ED",
    "phaseName": "Fase Regular",
    "levelName": "",
    "levelCode": "",
    "groupCode": "06",
    "phaseRound": 7,
    "roundNumber": 18,
    "homeTeam": "DROOP CENTRE C.B. L\u0027HOSPITALET",
    "homeScore": 78,
    "awayScore": 51,
    "awayTeam": "AEC COLLBLANC B",
    "isHome": true,
    "rivalTeamKey": "2025-2026::2A. TERRITORIAL SENIOR FEMENI::TEAM:83121",
    "rivalTeam": "AEC COLLBLANC B",
    "officialTeamScore": 78,
    "officialRivalScore": 51,
    "teamScore": 78,
    "rivalScore": 51,
    "result": "W",
    "topScorer": "GEMMA ROJALS SERRANO",
    "topScorerTeam": "DROOP CENTRE C.B. L\u0027HOSPITALET",
    "topScorerPoints": 17,
    "teamTopScorer": "GEMMA ROJALS SERRANO",
    "teamTopScorerPoints": 17,
    "insights": {
      "leadChanges": 4,
      "ties": 2,
      "maxLead": 27,
      "maxDeficit": 2,
      "bestRun": 15,
      "rivalBestRun": 7,
      "closingRun": 9,
      "rivalClosingRun": 0,
      "firstScorer": "NOA GARCIA OREJA",
      "firstScorerTeam": "DROOP CENTRE C.B. L\u0027HOSPITALET",
      "lastScorer": "GEMMA ROJALS SERRANO",
      "lastScorerTeam": "DROOP CENTRE C.B. L\u0027HOSPITALET",
      "teamFirstScorer": "NOA GARCIA OREJA",
      "teamLastScorer": "GEMMA ROJALS SERRANO",
      "bestPeriodLabel": "Parcial 1",
      "bestPeriodDiff": 11,
      "worstPeriodLabel": "Parcial 2",
      "worstPeriodDiff": 2,
      "periodScores": [
        {
          "periodNumber": 1,
          "label": "Parcial 1",
          "teamPoints": 26,
          "rivalPoints": 15,
          "diff": 11
        },
        {
          "periodNumber": 2,
          "label": "Parcial 2",
          "teamPoints": 14,
          "rivalPoints": 12,
          "diff": 2
        },
        {
          "periodNumber": 3,
          "label": "Parcial 3",
          "teamPoints": 19,
          "rivalPoints": 8,
          "diff": 11
        },
        {
          "periodNumber": 4,
          "label": "Parcial 4",
          "teamPoints": 19,
          "rivalPoints": 16,
          "diff": 3
        }
      ]
    },
    "matchReport": "",
    "matchReportGeneratedAtUtc": null,
    "matchReportModel": ""
  },
  {
    "teamKey": "2025-2026::2A. TERRITORIAL SENIOR FEMENI::TEAM:78662",
    "teamIdIntern": 543338,
    "teamIdExtern": 78662,
    "teamName": "DROOP CENTRE C.B. L\u0027HOSPITALET",
    "seasonStartYear": 2025,
    "seasonLabel": "2025-2026",
    "homeTeamKey": "2025-2026::2A. TERRITORIAL SENIOR FEMENI::TEAM:78662",
    "awayTeamKey": "2025-2026::2A. TERRITORIAL SENIOR FEMENI::TEAM:79306",
    "matchWebId": 18641,
    "matchInternId": 270368,
    "matchExternId": 1161581,
    "matchDate": "2026-03-14T16:45:00+01:00",
    "phaseNumber": 2,
    "sourcePhaseId": 19989,
    "categoryName": "2a. Territorial S\u00E8nior Femen\u00ED",
    "phaseName": "Fase Regular",
    "levelName": "",
    "levelCode": "",
    "groupCode": "06",
    "phaseRound": 8,
    "roundNumber": 19,
    "homeTeam": "DROOP CENTRE C.B. L\u0027HOSPITALET",
    "homeScore": 49,
    "awayScore": 61,
    "awayTeam": "UE BARBERA",
    "isHome": true,
    "rivalTeamKey": "2025-2026::2A. TERRITORIAL SENIOR FEMENI::TEAM:79306",
    "rivalTeam": "UE BARBERA",
    "officialTeamScore": 49,
    "officialRivalScore": 61,
    "teamScore": 49,
    "rivalScore": 61,
    "result": "L",
    "topScorer": "LAURA PEREZ FABREGA",
    "topScorerTeam": "UE BARBERA",
    "topScorerPoints": 15,
    "teamTopScorer": "LAIA MOLINA QUILES",
    "teamTopScorerPoints": 11,
    "insights": {
      "leadChanges": 3,
      "ties": 4,
      "maxLead": 11,
      "maxDeficit": 13,
      "bestRun": 6,
      "rivalBestRun": 10,
      "closingRun": 0,
      "rivalClosingRun": 1,
      "firstScorer": "GEMMA ROJALS SERRANO",
      "firstScorerTeam": "DROOP CENTRE C.B. L\u0027HOSPITALET",
      "lastScorer": "MARIA JOSE GOMEZ LOPEZ",
      "lastScorerTeam": "UE BARBERA",
      "teamFirstScorer": "GEMMA ROJALS SERRANO",
      "teamLastScorer": "INGRID TERMENS GUMA",
      "bestPeriodLabel": "Parcial 1",
      "bestPeriodDiff": 9,
      "worstPeriodLabel": "Parcial 2",
      "worstPeriodDiff": -14,
      "periodScores": [
        {
          "periodNumber": 1,
          "label": "Parcial 1",
          "teamPoints": 17,
          "rivalPoints": 8,
          "diff": 9
        },
        {
          "periodNumber": 2,
          "label": "Parcial 2",
          "teamPoints": 11,
          "rivalPoints": 25,
          "diff": -14
        },
        {
          "periodNumber": 3,
          "label": "Parcial 3",
          "teamPoints": 12,
          "rivalPoints": 10,
          "diff": 2
        },
        {
          "periodNumber": 4,
          "label": "Parcial 4",
          "teamPoints": 9,
          "rivalPoints": 18,
          "diff": -9
        }
      ]
    },
    "matchReport": "",
    "matchReportGeneratedAtUtc": null,
    "matchReportModel": ""
  },
  {
    "teamKey": "2025-2026::2A. TERRITORIAL SENIOR FEMENI::TEAM:78662",
    "teamIdIntern": 545453,
    "teamIdExtern": 78662,
    "teamName": "DROOP CENTRE C.B. L\u0027HOSPITALET",
    "seasonStartYear": 2025,
    "seasonLabel": "2025-2026",
    "homeTeamKey": "2025-2026::2A. TERRITORIAL SENIOR FEMENI::TEAM:81851",
    "awayTeamKey": "2025-2026::2A. TERRITORIAL SENIOR FEMENI::TEAM:78662",
    "matchWebId": 18660,
    "matchInternId": 271425,
    "matchExternId": 1160421,
    "matchDate": "2026-03-15T18:00:00+01:00",
    "phaseNumber": 2,
    "sourcePhaseId": 19989,
    "categoryName": "2a. Territorial S\u00E8nior Femen\u00ED",
    "phaseName": "Fase Regular",
    "levelName": "",
    "levelCode": "",
    "groupCode": "06",
    "phaseRound": 9,
    "roundNumber": 20,
    "homeTeam": "B\u00C0SQUET NOU BARRIS",
    "homeScore": 63,
    "awayScore": 60,
    "awayTeam": "DROOP CENTRE C.B. L\u0027HOSPITALET",
    "isHome": false,
    "rivalTeamKey": "2025-2026::2A. TERRITORIAL SENIOR FEMENI::TEAM:81851",
    "rivalTeam": "B\u00C0SQUET NOU BARRIS",
    "officialTeamScore": 60,
    "officialRivalScore": 63,
    "teamScore": 60,
    "rivalScore": 63,
    "result": "L",
    "topScorer": "LUC\u00CDA D\u00CDAZ MARIAS",
    "topScorerTeam": "B\u00C0SQUET NOU BARRIS",
    "topScorerPoints": 14,
    "teamTopScorer": "INGRID TERMENS GUMA",
    "teamTopScorerPoints": 14,
    "insights": {
      "leadChanges": 1,
      "ties": 4,
      "maxLead": 4,
      "maxDeficit": 14,
      "bestRun": 9,
      "rivalBestRun": 7,
      "closingRun": 0,
      "rivalClosingRun": 6,
      "firstScorer": "LUC\u00CDA D\u00CDAZ MARIAS",
      "firstScorerTeam": "B\u00C0SQUET NOU BARRIS",
      "lastScorer": "ALBA GUERRERO GARCIA",
      "lastScorerTeam": "B\u00C0SQUET NOU BARRIS",
      "teamFirstScorer": "INGRID TERMENS GUMA",
      "teamLastScorer": "INGRID TERMENS GUMA",
      "bestPeriodLabel": "Parcial 2",
      "bestPeriodDiff": 1,
      "worstPeriodLabel": "Parcial 1",
      "worstPeriodDiff": -4,
      "periodScores": [
        {
          "periodNumber": 1,
          "label": "Parcial 1",
          "teamPoints": 18,
          "rivalPoints": 22,
          "diff": -4
        },
        {
          "periodNumber": 2,
          "label": "Parcial 2",
          "teamPoints": 12,
          "rivalPoints": 11,
          "diff": 1
        },
        {
          "periodNumber": 3,
          "label": "Parcial 3",
          "teamPoints": 17,
          "rivalPoints": 17,
          "diff": 0
        },
        {
          "periodNumber": 4,
          "label": "Parcial 4",
          "teamPoints": 13,
          "rivalPoints": 13,
          "diff": 0
        }
      ]
    },
    "matchReport": "",
    "matchReportGeneratedAtUtc": null,
    "matchReportModel": ""
  },
  {
    "teamKey": "2025-2026::2A. TERRITORIAL SENIOR FEMENI::TEAM:78662",
    "teamIdIntern": 549832,
    "teamIdExtern": 78662,
    "teamName": "DROOP CENTRE C.B. L\u0027HOSPITALET",
    "seasonStartYear": 2025,
    "seasonLabel": "2025-2026",
    "homeTeamKey": "2025-2026::2A. TERRITORIAL SENIOR FEMENI::TEAM:78662",
    "awayTeamKey": "2025-2026::2A. TERRITORIAL SENIOR FEMENI::TEAM:81725",
    "matchWebId": 18671,
    "matchInternId": 273615,
    "matchExternId": 1160514,
    "matchDate": "2026-03-22T13:30:00+01:00",
    "phaseNumber": 2,
    "sourcePhaseId": 19989,
    "categoryName": "2a. Territorial S\u00E8nior Femen\u00ED",
    "phaseName": "Fase Regular",
    "levelName": "",
    "levelCode": "",
    "groupCode": "06",
    "phaseRound": 10,
    "roundNumber": 21,
    "homeTeam": "DROOP CENTRE C.B. L\u0027HOSPITALET",
    "homeScore": 45,
    "awayScore": 61,
    "awayTeam": "CB ABRERA",
    "isHome": true,
    "rivalTeamKey": "2025-2026::2A. TERRITORIAL SENIOR FEMENI::TEAM:81725",
    "rivalTeam": "CB ABRERA",
    "officialTeamScore": 45,
    "officialRivalScore": 61,
    "teamScore": 45,
    "rivalScore": 61,
    "result": "L",
    "topScorer": "AINA SITGES AMAT",
    "topScorerTeam": "CB ABRERA",
    "topScorerPoints": 16,
    "teamTopScorer": "LAIA NIUBO PERELLO",
    "teamTopScorerPoints": 15,
    "insights": {
      "leadChanges": 3,
      "ties": 2,
      "maxLead": 12,
      "maxDeficit": 16,
      "bestRun": 11,
      "rivalBestRun": 16,
      "closingRun": 0,
      "rivalClosingRun": 16,
      "firstScorer": "AINA SITGES AMAT",
      "firstScorerTeam": "CB ABRERA",
      "lastScorer": "DULCE POLO PEREZ",
      "lastScorerTeam": "CB ABRERA",
      "teamFirstScorer": "GEMMA ROJALS SERRANO",
      "teamLastScorer": "ANDREA ESPADA PEREZ",
      "bestPeriodLabel": "Parcial 1",
      "bestPeriodDiff": 6,
      "worstPeriodLabel": "Parcial 4",
      "worstPeriodDiff": -17,
      "periodScores": [
        {
          "periodNumber": 1,
          "label": "Parcial 1",
          "teamPoints": 12,
          "rivalPoints": 6,
          "diff": 6
        },
        {
          "periodNumber": 2,
          "label": "Parcial 2",
          "teamPoints": 19,
          "rivalPoints": 21,
          "diff": -2
        },
        {
          "periodNumber": 3,
          "label": "Parcial 3",
          "teamPoints": 8,
          "rivalPoints": 11,
          "diff": -3
        },
        {
          "periodNumber": 4,
          "label": "Parcial 4",
          "teamPoints": 6,
          "rivalPoints": 23,
          "diff": -17
        }
      ]
    },
    "matchReport": "",
    "matchReportGeneratedAtUtc": null,
    "matchReportModel": ""
  },
  {
    "teamKey": "2025-2026::2A. TERRITORIAL SENIOR FEMENI::TEAM:78662",
    "teamIdIntern": 555063,
    "teamIdExtern": 78662,
    "teamName": "DROOP CENTRE C.B. L\u0027HOSPITALET",
    "seasonStartYear": 2025,
    "seasonLabel": "2025-2026",
    "homeTeamKey": "2025-2026::2A. TERRITORIAL SENIOR FEMENI::TEAM:83244",
    "awayTeamKey": "2025-2026::2A. TERRITORIAL SENIOR FEMENI::TEAM:78662",
    "matchWebId": 18674,
    "matchInternId": 276230,
    "matchExternId": 1068598,
    "matchDate": "2026-04-11T19:45:00+02:00",
    "phaseNumber": 2,
    "sourcePhaseId": 19989,
    "categoryName": "2a. Territorial S\u00E8nior Femen\u00ED",
    "phaseName": "Fase Regular",
    "levelName": "",
    "levelCode": "",
    "groupCode": "06",
    "phaseRound": 11,
    "roundNumber": 22,
    "homeTeam": "CE LA MARINA",
    "homeScore": 55,
    "awayScore": 54,
    "awayTeam": "DROOP CENTRE C.B. L\u0027HOSPITALET",
    "isHome": false,
    "rivalTeamKey": "2025-2026::2A. TERRITORIAL SENIOR FEMENI::TEAM:83244",
    "rivalTeam": "CE LA MARINA",
    "officialTeamScore": 54,
    "officialRivalScore": 55,
    "teamScore": 54,
    "rivalScore": 55,
    "result": "L",
    "topScorer": "GEMMA ROJALS SERRANO",
    "topScorerTeam": "DROOP CENTRE C.B. L\u0027HOSPITALET",
    "topScorerPoints": 17,
    "teamTopScorer": "GEMMA ROJALS SERRANO",
    "teamTopScorerPoints": 17,
    "insights": {
      "leadChanges": 0,
      "ties": 0,
      "maxLead": 0,
      "maxDeficit": 16,
      "bestRun": 6,
      "rivalBestRun": 10,
      "closingRun": 3,
      "rivalClosingRun": 0,
      "firstScorer": "ANA MARTINEZ PEIRO",
      "firstScorerTeam": "CE LA MARINA",
      "lastScorer": "INGRID TERMENS GUMA",
      "lastScorerTeam": "DROOP CENTRE C.B. L\u0027HOSPITALET",
      "teamFirstScorer": "GEMMA ROJALS SERRANO",
      "teamLastScorer": "INGRID TERMENS GUMA",
      "bestPeriodLabel": "Parcial 4",
      "bestPeriodDiff": 5,
      "worstPeriodLabel": "Parcial 1",
      "worstPeriodDiff": -10,
      "periodScores": [
        {
          "periodNumber": 1,
          "label": "Parcial 1",
          "teamPoints": 9,
          "rivalPoints": 19,
          "diff": -10
        },
        {
          "periodNumber": 2,
          "label": "Parcial 2",
          "teamPoints": 15,
          "rivalPoints": 11,
          "diff": 4
        },
        {
          "periodNumber": 3,
          "label": "Parcial 3",
          "teamPoints": 10,
          "rivalPoints": 10,
          "diff": 0
        },
        {
          "periodNumber": 4,
          "label": "Parcial 4",
          "teamPoints": 20,
          "rivalPoints": 15,
          "diff": 5
        }
      ]
    },
    "matchReport": "",
    "matchReportGeneratedAtUtc": null,
    "matchReportModel": ""
  }
]